npeg/__init__.py
npeg/base_img.py
npeg/bindings/__init__.py
npeg/bindings/_npeg_core.dll
npeg/bindings/_npeg_core.so
npeg/bindings/img_result_struct.py
npeg/bindings/img_struct.py
npeg/bindings/interpolation.py
npeg/bindings/matrix_struct.py
npeg/bindings/pbm_img_struct.py
npeg/exceptions.py
npeg/matrix.py
npeg/pbm_img.py
npeg/py.typed
npeg-0.0.1.dist-info/LICENSE
npeg-0.0.1.dist-info/METADATA
npeg-0.0.1.dist-info/WHEEL
npeg-0.0.1.dist-info/entry_points.txt
npeg-0.0.1.dist-info/RECORD
