Metadata-Version: 2.1
Name: npeg
Version: 0.0.1
Summary: Small and blazingly fast python library for image processing.
License: GPLv3
Keywords: img,avx,opencl,cuda,processing,computation
Author: NeoTheBestDeveloper
Author-email: kiankasey91n@gmail.com
Requires-Python: >=3.10,<4.0
Classifier: Development Status :: 2 - Pre-Alpha
Classifier: Environment :: GPU
Classifier: License :: OSI Approved :: GNU General Public License v3 (GPLv3)
Classifier: License :: Other/Proprietary License
Classifier: Operating System :: Microsoft :: Windows :: Windows 10
Classifier: Operating System :: POSIX :: Linux
Classifier: Programming Language :: Python :: 3
Classifier: Programming Language :: Python :: 3.10
Classifier: Programming Language :: Python :: 3.11
Classifier: Programming Language :: Python :: 3
Classifier: Programming Language :: Python :: 3.10
